AUTHORS
BUGS.md
CHANGES.rst
LICENSE
MANIFEST.in
README.rst
TODO.md
setup.py
ailib/__init__.py
ailib.egg-info/PKG-INFO
ailib.egg-info/SOURCES.txt
ailib.egg-info/dependency_links.txt
ailib.egg-info/requires.txt
ailib.egg-info/top_level.txt
docs/AIMA
docs/Makefile
docs/api.rst
docs/api_optimize_functions_noise.rst
docs/api_optimize_functions_unconstrained.rst
docs/conf.py
docs/developer.rst
docs/index.rst
docs/init_sphinx.sh
docs/intro.rst
docs/make.bat
docs/gallery/gallery_jupyter.zip
docs/gallery/gallery_python.zip
docs/gallery/index.rst
docs/gallery/mdp_framework_example.ipynb
docs/gallery/mdp_framework_example.py
docs/gallery/mdp_framework_example.rst
docs/gallery/optimization_framework_example.ipynb
docs/gallery/optimization_framework_example.py
docs/gallery/optimization_framework_example.rst
docs/gallery/images/thumb/sphx_glr_mdp_framework_example_thumb.png
docs/gallery/images/thumb/sphx_glr_optimization_framework_example_thumb.png
examples/mdp_framework_example.py
examples/optimization_framework_example.py